subarulink/__init__.py
subarulink/__version__.py
subarulink/connection.py
subarulink/const.py
subarulink/controller.py
subarulink/exceptions.py
subarulink/_subaru_api/__init__.py
subarulink/_subaru_api/const.py
subarulink/app/__init__.py
subarulink/app/cli.py
subarulink-0.7.18.dist-info/licenses/LICENSE
subarulink-0.7.18.dist-info/METADATA
subarulink-0.7.18.dist-info/WHEEL
subarulink-0.7.18.dist-info/entry_points.txt
subarulink-0.7.18.dist-info/top_level.txt
subarulink-0.7.18.dist-info/RECORD
