Metadata-Version: 2.4
Name: subarulink
Version: 0.7.18
Summary: A package for interacting with the MySubaru Connected Services API.
Author: G-Two
License-Expression: Apache-2.0
Project-URL: Homepage, https://github.com/G-Two/subarulink
Project-URL: Repository, https://github.com/G-Two/subarulink
Classifier: Development Status :: 3 - Alpha
Classifier: Intended Audience :: Developers
Classifier: Operating System :: OS Independent
Classifier: Programming Language :: Python :: 3.12
Classifier: Topic :: Internet
Requires-Python: >=3.12
License-File: LICENSE
Requires-Dist: aiohttp
Requires-Dist: stdiomask
Dynamic: license-file
